pyfembed/__init__.py
pyfembed/pyfembed_class.py
pyfembed/interfaces/__init__.py
pyfembed-0.1.6.dist-info/LICENSE
pyfembed-0.1.6.dist-info/METADATA
pyfembed-0.1.6.dist-info/WHEEL
pyfembed-0.1.6.dist-info/top_level.txt
pyfembed-0.1.6.dist-info/RECORD
