Metadata-Version: 2.1
Name: pyfembed
Version: 0.1.6
Summary: Upload video with the Fembed API
Home-page: https://github.com/raishid/pyfembed
Author: raishid
Author-email: raishidavid@gmail.com
License-File: LICENSE
Requires-Dist: requests
Requires-Dist: tus.py
